<FDesign>
	<Table InternalName="25FF85AF-4C4F-484b-B5E5-4A4C269FC1A7">
		<Definition DisplayName="ISO 14 - Light serie">
			<Columns>
				<Name />
				<n Units="ul" />
				<d Units="mm" />
				<D Units="mm" />
				<s Units="mm" />
				<R Units="mm" />
				<l Units="mm" />
			</Columns>
		</Definition>
		<Data>		
			<Row>
				<Name>6x23x26</Name>
				<n>6</n>
				<d>23</d>
				<D>26</D>
				<b>6</b>
				<s>0.3</s>
				<R>0.1</R>
				<l>7BC17020-D979-40c1-80C4-7BB24E8EB36D</l>
			</Row>
			<Row>
				<Name>6x26x30</Name>
				<n>6</n>
				<d>26</d>
				<D>30</D>
				<b>6</b>
				<s>0.3</s>
				<R>0.1</R>
				<l>7BC17020-D979-40c1-80C4-7BB24E8EB36D</l>
			</Row>
			<Row>
				<Name>6x28x32</Name>
				<n>6</n>
				<d>28</d>
				<D>32</D>
				<b>7</b>
				<s>0.3</s>
				<R>0.1</R>
				<l>7BC17020-D979-40c1-80C4-7BB24E8EB36D</l>
			</Row>
			<Row
				><Name>8x32x36</Name>
				<n>8</n>
				<d>32</d>
				<D>36</D>
				<b>6</b>
				<s>0.4</s>
				<R>0.1</R>
				<l>7BC17020-D979-40c1-80C4-7BB24E8EB36D</l>
			</Row>
			<Row>
				<Name>8x36x40</Name>
				<n>8</n>
				<d>36</d>
				<D>40</D>
				<b>7</b>
				<s>0.4</s>
				<R>0.1</R>
				<l>7BC17020-D979-40c1-80C4-7BB24E8EB36D</l>
			</Row>
			<Row>
				<Name>8x42x46</Name>
				<n>8</n>
				<d>42</d>
				<D>46</D>
				<b>8</b>
				<s>0.4</s>
				<R>0.1</R>
				<l>7BC17020-D979-40c1-80C4-7BB24E8EB36D</l>
			</Row>
			<Row>
				<Name>8x46x50</Name>
				<n>8</n>
				<d>46</d>
				<D>50</D>
				<b>9</b>
				<s>0.4</s>
				<R>0.1</R>
				<l>7BC17020-D979-40c1-80C4-7BB24E8EB36D</l>
			</Row>
			<Row>
				<Name>8x52x58</Name>
				<n>8</n>
				<d>52</d>
				<D>58</D>
				<b>10</b>
				<s>0.5</s>
				<R>0.1</R>
				<l>7BC17020-D979-40c1-80C4-7BB24E8EB36D</l>
			</Row>
			<Row>
				<Name>8x56x62</Name>
				<n>8</n>
				<d>56</d>
				<D>62</D>
				<b>10</b>
				<s>0.5</s>
				<R>0.1</R>
				<l>7BC17020-D979-40c1-80C4-7BB24E8EB36D</l>
			</Row>
			<Row>
				<Name>8x62x68</Name>
				<n>8</n>
				<d>62</d>
				<D>68</D>
				<b>12</b>
				<s>0.5</s>
				<R>0.1</R>
				<l>7BC17020-D979-40c1-80C4-7BB24E8EB36D</l>
			</Row>
			<Row>
				<Name>10x72x78</Name>
				<n>10</n>
				<d>72</d>
				<D>78</D>
				<b>12</b>
				<s>0.5</s>
				<R>0.1</R>
				<l>7BC17020-D979-40c1-80C4-7BB24E8EB36D</l>
			</Row>
			<Row>
				<Name>10x82x88</Name>
				<n>10</n>
				<d>82</d>
				<D>88</D>
				<b>12</b>
				<s>0.5</s>
				<R>0.1</R>
				<l>7BC17020-D979-40c1-80C4-7BB24E8EB36D</l>
			</Row>
			<Row>
				<Name>10x92x98</Name>
				<n>10</n>
				<d>92</d>
				<D>98</D>
				<b>14</b>
				<s>0.5</s>
				<R>0.1</R>
				<l>7BC17020-D979-40c1-80C4-7BB24E8EB36D</l>
			</Row>
			<Row>
				<Name>10x102x108</Name>
				<n>10</n>
				<d>102</d>
				<D>108</D>
				<b>16</b>
				<s>0.5</s>
				<R>0.1</R>
				<l>7BC17020-D979-40c1-80C4-7BB24E8EB36D</l>
			</Row>
			<Row>
			<Name>10x112x120</Name>
				<n>10</n>
				<d>112</d>
				<D>120</D>
				<b>18</b>
				<s>0.5</s>
				<R>0.1</R>
				<l>7BC17020-D979-40c1-80C4-7BB24E8EB36D</l>
			</Row>
		</Data>
	</Table>
</FDesign>	